{
    "__rev__":  "Rev: 2025-09-30 18:00 r1",
    "items":  [
                  {
                      "id":  "login_smoke",
                      "type":  "screen",
                      "title":  "Admin login duman testi",
                      "url":  "/admin/login/",
                      "login":  {
                                    "username":  "hp",
                                    "password":  "Admin!2345"
                                },
                      "checks":  {
                                     "must_have_selectors":  [
                                                                 "input[name=username]",
                                                                 "input[name=password]"
                                                             ],
                                     "required_text":  [
                                                           "Username",
                                                           "Password",
                                                           "Log in"
                                                       ],
                                     "allow_extra_text":  true,
                                     "min_text_hit_rate":  1.0
                                 },
                      "design_ref":  "targets/reference/admin_login.png",
                      "visual_threshold":  0.85
                  },
                  {
                      "id":  "equipment_ui",
                      "type":  "crud_admin",
                      "title":  "Equipment admin CRUD UI",
                      "app":  "maintenance",
                      "model":  "equipment",
                      "urls":  {
                                   "add":  "/admin/maintenance/equipment/add/",
                                   "list_direct":  "/admin/maintenance/equipment/_direct/"
                               },
                      "selectors":  {
                                        "form":  "form",
                                        "list_table":  "table#result_list",
                                        "row_link":  "table#result_list tbody tr:first-child th \u003e a",
                                        "delete_btn":  "a.deletelink",
                                        "delete_confirm":  "form[action$=\"/delete/\"] input[type=submit]",
                                        "msg":  ".messagelist"
                                    },
                      "data":  {
                                   "code":  "EQP-CRUD-UI",
                                   "name":  "UI CRUD Equipment 1",
                                   "name_updated":  "UI CRUD Equipment 1 guncellendi",
                                   "search_q":  "EQP-CRUD-UI"
                               },
                      "checks":  {
                                     "required_text":  [
                                                           "Equipment",
                                                           "Add equipment",
                                                           "Filter"
                                                       ],
                                     "allow_extra_text":  true,
                                     "min_text_hit_rate":  1.0
                                 },
                      "ensure_cmd":  "",
                      "design_ref":  "targets/reference/equipment_list.png",
                      "visual_threshold":  0.9
                  }
              ]
}